LICENSE
MANIFEST.in
README.md
setup.cfg
setup.py
isacalc/__init__.py
isacalc/isa.json
isacalc.egg-info/PKG-INFO
isacalc.egg-info/SOURCES.txt
isacalc.egg-info/dependency_links.txt
isacalc.egg-info/requires.txt
isacalc.egg-info/top_level.txt
isacalc/scripts/isa_main.py
isacalc/src/__init__.py
isacalc/src/atmosphere.py
isacalc/src/layers.py
isacalc/src/__pycache__/__init__.cpython-312.pyc
isacalc/src/__pycache__/atmosphere.cpython-312.pyc
isacalc/src/__pycache__/layers.cpython-312.pyc