Metadata-Version: 2.2
Name: isacalc
Version: 1.3.4
Summary: Standard International Atmosphere Calculator
Home-page: https://github.com/LukeDeWaal/ISA_Calculator
Download-URL: https://github.com/LukeDeWaal/ISA_Calculator/archive/v1.3.4.tar.gz
Author: Luke de Waal
Author-email: lr.de.waal.01@gmail.com
License: GNU GPLv3
Keywords: ISA,Aerospace,Aeronautical,Atmosphere
Classifier: Development Status :: 4 - Beta
Classifier: Intended Audience :: Developers
Classifier: Topic :: Software Development :: Build Tools
Classifier: License :: OSI Approved :: GNU General Public License v3 (GPLv3)
Classifier: Programming Language :: Python :: 3.11
Classifier: Programming Language :: Python :: 3.12
License-File: LICENSE
Requires-Dist: numpy
Requires-Dist: pandas
Requires-Dist: tabulate
Dynamic: author
Dynamic: author-email
Dynamic: classifier
Dynamic: description
Dynamic: description-content-type
Dynamic: download-url
Dynamic: home-page
Dynamic: keywords
Dynamic: license
Dynamic: requires-dist
Dynamic: summary
